{
  "project": "Node.js Interview Practical APIs",
  "requests": [
    {
      "section": "Basic Server & Routing",
      "question": "Q01 - Create Basic Express Server",
      "folder": "basic-server-routing/Q01-basic-express-server",
      "method": "GET",
      "baseUrl": "http://localhost:5000",
      "url": "/",
      "body": null
    },
    {
      "section": "Basic Server & Routing",
      "question": "Q03 - POST API (Read Body)",
      "folder": "basic-server-routing/Q03-post-api-read-body",
      "method": "POST",
      "baseUrl": "http://localhost:5000",
      "url": "/api/user",
      "body": {
        "name": "Ronit"
      }
    },
    {
      "section": "Basic Server & Routing",
      "question": "Q04 - PUT API (Update Data)",
      "folder": "basic-server-routing/Q04-put-api-update-data",
      "method": "PUT",
      "baseUrl": "http://localhost:5000",
      "url": "/api/user",
      "body": {
        "name": "Updated Dummy User"
      }
    },
    {
      "section": "Middleware",
      "question": "Q06 - Logger Middleware",
      "folder": "middleware/Q06-logger-middleware",
      "method": "GET",
      "baseUrl": "http://localhost:5000",
      "url": "/",
      "body": null
    },
    {
      "section": "Middleware",
      "question": "Q07 - Time Logger Middleware",
      "folder": "middleware/Q07-time-logger-middleware",
      "method": "GET",
      "baseUrl": "http://localhost:5000",
      "url": "/",
      "body": null
    },
    {
      "section": "Middleware",
      "question": "Q08 - Custom Middleware (Auth Check)",
      "folder": "middleware/Q08-custom-auth-middleware",
      "method": "GET",
      "baseUrl": "http://localhost:5000",
      "url": "/secure-data?token=123",
      "body": null
    },
    {
      "section": "Middleware",
      "question": "Q09 - Apply Middleware to Specific Route",
      "folder": "middleware/Q09-route-specific-middleware",
      "method": "GET",
      "baseUrl": "http://localhost:5000",
      "url": "/admin",
      "body": null
    },
    {
      "section": "Request Handling",
      "question": "Q10 - Query Params Handling",
      "folder": "request-handling/Q10-query-params-handling",
      "method": "GET",
      "baseUrl": "http://localhost:5000",
      "url": "/search?name=NodeJS",
      "body": null
    },
    {
      "section": "Request Handling",
      "question": "Q12 - Validate Request Body (Manual)",
      "folder": "request-handling/Q12-validate-request-body",
      "method": "POST",
      "baseUrl": "http://localhost:5000",
      "url": "/api/user",
      "body": {}
    },
    {
      "section": "CRUD (In-Memory Data)",
      "question": "Q14 - Create User (Array Storage)",
      "folder": "crud-in-memory-data/Q14-create-user-array-storage",
      "method": "POST",
      "baseUrl": "http://localhost:5000",
      "url": "/users",
      "body": {
        "name": "Maya"
      }
    },
    {
      "section": "Async & Error Handling",
      "question": "Q19 - Async API using async/await",
      "folder": "async-error-handling/Q19-async-await-api",
      "method": "GET",
      "baseUrl": "http://localhost:5000",
      "url": "/async-data",
      "body": null
    },
    {
      "section": "Async & Error Handling",
      "question": "Q20 - Try-Catch Error Handling",
      "folder": "async-error-handling/Q20-try-catch-error-handling",
      "method": "GET",
      "baseUrl": "http://localhost:5000",
      "url": "/error-demo",
      "body": null
    },
    {
      "section": "Async & Error Handling",
      "question": "Q21 - Global Error Handler",
      "folder": "async-error-handling/Q21-global-error-handler",
      "method": "GET",
      "baseUrl": "http://localhost:5000",
      "url": "/error-demo",
      "body": null
    },
    {
      "section": "Real Features",
      "question": "Q22 - Environment Variables (dotenv)",
      "folder": "real-features/Q22-dotenv-environment-variable",
      "method": "GET",
      "baseUrl": "http://localhost:5000",
      "url": "/",
      "body": null
    },
    {
      "section": "Real Features",
      "question": "Q24 - Pagination API",
      "folder": "real-features/Q24-pagination-api",
      "method": "GET",
      "baseUrl": "http://localhost:5000",
      "url": "/users?page=1&limit=3",
      "body": null
    },
    {
      "section": "Real Features",
      "question": "Q25 - Search Filter API",
      "folder": "real-features/Q25-search-filter-api",
      "method": "GET",
      "baseUrl": "http://localhost:5000",
      "url": "/users?name=al",
      "body": null
    },
    {
      "section": "Authentication Basics",
      "question": "Q27 - Hash Password using bcrypt",
      "folder": "authentication-basics/Q27-hash-password-bcrypt",
      "method": "POST",
      "baseUrl": "http://localhost:5000",
      "url": "/hash-password",
      "body": {
        "password": "mySecret123"
      }
    },
    {
      "section": "Authentication Basics",
      "question": "Q30 - Verify JWT Token Middleware",
      "folder": "authentication-basics/Q30-verify-jwt-token-middleware",
      "method": "GET",
      "baseUrl": "http://localhost:5000",
      "url": "/profile",
      "headers": {
        "Authorization": "Bearer paste_valid_jwt_token_here"
      },
      "body": null
    }
  ]
}
